gtfs_kit_polars/__init__.py
gtfs_kit_polars/calendar.py
gtfs_kit_polars/cleaners.py
gtfs_kit_polars/constants.py
gtfs_kit_polars/feed.py
gtfs_kit_polars/helpers.py
gtfs_kit_polars/miscellany.py
gtfs_kit_polars/routes.py
gtfs_kit_polars/shapes.py
gtfs_kit_polars/stop_times.py
gtfs_kit_polars/stops.py
gtfs_kit_polars/trips.py
gtfs_kit_polars-1.0.0.dist-info/METADATA
gtfs_kit_polars-1.0.0.dist-info/WHEEL
gtfs_kit_polars-1.0.0.dist-info/licenses/LICENSE.txt
gtfs_kit_polars-1.0.0.dist-info/RECORD
