Metadata-Version: 2.4
Name: gtfs-kit-polars
Version: 1.0.0
Summary: A Python library for analyzing GTFS feeds.
Project-URL: Repository, https://github.com/mrcagney/gtfs_kit_polars
Project-URL: Documentation, https://mrcagney.github.io/gtfs_kit_polars_docs
Author-email: Alexander Raichev <araichev@mrcagney.com>
License-Expression: MIT
License-File: LICENSE.txt
Requires-Python: >=3.12
Requires-Dist: folium>=0
Requires-Dist: geopandas>=1
Requires-Dist: json2html>=1
Requires-Dist: pandas>=2.2.2
Requires-Dist: polars-st>=0.3.0
Requires-Dist: polars>=1.34
Requires-Dist: requests>=2
Requires-Dist: rtree>=0
Requires-Dist: shapely>=1.8
Requires-Dist: utm>=0.8.1
